{"id_art": "475b72cbc1089c0294acc0569bf8be2f", "title": "Mandon invite Cambadelis a quitter la direction du PS", "newspaper": "Le Figaro", "author": ["Arthur Berdah"], "date_publi": "2017-05-29", "content": "D'une bataille a l'autre. Apres la deroute de la presidentielle, et avant celle - annoncee - des legislatives, le Parti socialiste semble etre deja  en proie aux guerres intestines pour savoir qui en prendra la tete  a la rentree. Au coeur des attaques se trouve Jean-Christophe Cambadelis, dont plusieurs cadres reclament la tete. C'est le cas de l'ancien secretaire d'Etat a la Recherche et a l'Enseignement superieur, Thierry Mandon, qui a decide d'ouvrir le feu contre le depute de Paris dans les colonnes de  L'Opinion . <<Il a precise qu'il fallait tout changer mais qu'il resterait au centre de ce changement. C'est surprenant. Tout changer, cela passe aussi par un changement de direction, pour pouvoir passer le relais a une nouvelle generation>>, assene  le futur-ex-depute de l'Essonne  au sujet du patron de Solferino. <<Il faudrait, au soir des legislatives, nommer une direction collegiale de six a huit responsables>>, poursuit-il, citant Najat Vallaud-Belkacem, Matthias Fekl, Olivier Faure, Guillaume Balas, et d'autres <<jeunes elus locaux>>. Cambadelis fera des <<propositions>> le 18 juin Selon Thierry Mandon, ces personnalites emergentes <<devraient avoir la charge de conduire des assises de la reconstruction, embrassant toutes les questions, ouvertes largement sur la societe et qui pourraient preparer un congres fondateur d'un nouveau Parti socialiste, democratique, social et ecologique. Sans se precipiter>>, espere-t-il. <<Nous devons construire un parti d'ajourd'hui>>, exhorte-t-il encore. Affirmant que <<le Parti socialiste ne va pas disparaitre>>,  il s'interroge enfin sur l'utilite reelle d'un <<changement de nom>> . Cette sortie n'a pas ete tres appreciee par l'interesse, qui a tenu a y repondre des ce lundi matin. Invite de  France Info , Jean-Christophe Cambadelis a denonce <<les genies de village qui font des declarations dans leur coin, pour leur pomme, alors qu'ils ne seront pas candidats>> et a invite son detracteur a <<quand meme prendre en compte l'esprit collectif>>. <<La premiere des propositions, c'est qu'il n'y a pas de refondation s'il n'y a pas de retour a l'esprit collectif>>, a-t-il estime. <<Et le deuxieme element, c'est que maintenant, les militants doivent pouvoir intervenir dans ce qui sera la refondation. Il faut un processus collectif et je m'y emploierai>>, a-t-il ensuite annonce, reaffirmant qu'il <<ferait des propositions le 18 juin>>. Un propos qui tranche avec  ce qu'il declarait le 20 avril dernier sur France 5 . <<Je ne tire aucune lecon (de cette presidentielle) parce que je pense (qu'elle) est tellement atypique qu'on ne peut pas en tirer des lecons politiques. C'est mon analyse>>, affirmait-il alors.", "theme": "politique"}