{"id_art": "28172942828b93d2dc01153140b5c6b0", "title": "Pierre-Ambroise Bosse sur son agression: <<Il y a des gens dangereux>>", "newspaper": "Le Figaro", "author": ["Le Scan Sport"], "date_publi": "2017-09-10", "content": "Premiere sortie officielle pour Pierre-Ambroise Bosse. Le champion du monde du 800 m, qui a failli perdre l'usage d'un oeil lors de l'agression dont il a ete victime au petit matin du 27 aout, a indique samedi a Angers qu'il allait <<beaucoup mieux>>. <<Ca va beaucoup mieux. Je ne ressemblais pas a ca il y a deux semaines. Les choses, en surface, se sont resorbees assez vite parce que le corps humain, quand on est en forme, il bosse>>, a explique l'athlete age de 25 ans, en marge du DecaNation qu'il a suivi en spectateur aupres de sa famille. \n                                 \n                                     Ce qui m'a vraiment touche, c'est des gens qui ont vecu des choses bien plus traumatisantes que moi et qui me racontent des choses qu'ils ne racontent meme pas a leur psy     \n                             L'agression <<n'est pas une histoire personnelle. C'est surtout qu'il y a des gens dangereux qui doivent comprendre qu'ils sont dangereux. Ils ont touche ma tete. Ils ont pu mettre en danger ma vie d'athlete. Moi, je suis un non violent>>, a souligne le medaille d'or des Mondiaux de Londres. Bosse a ete agresse a 4h00 du matin sur le parking du casino de Gujan-Mestras (Gironde), la ville de son club formateur. Un homme de 24 ans a ete mis en examen trois jours plus tard et une information judiciaire ouverte pour <<violences en reunion>> afin de retrouver d'autres suspects.  <<Il y a plein de gens qui m'ont soutenu. Ce qui m'a vraiment touche, c'est des gens qui ont vecu des choses bien plus traumatisantes que moi et qui me racontent des choses qu'ils ne racontent meme pas a leur psy>>, a ajoute Pierre-Amboise Bosse. Le champion du monde n'a pas de date de reprise d'entrainement. <<Pour l'instant, je fatigue vite. Je n'ai pas de peps, je n'ai pas envie de faire du sport. Je n'ai pas recupere de ma medaille d'or>>, a-t-il remarque. Mais, l'or de Londres n'est pas une fin. <<J'ai encore des envies, faire mieux, ameliorer mon record personnel, mieux gerer tactiquement mes courses>>. Bosse compte repartir en Australie l'hiver venu pour se ressourcer, vivre et s'entrainer. Une recette qu'il avait experimentee avec succes cette annee.", "theme": "le scan sport"}